py_unidbg_server/__init__.py
py_unidbg_server/unidbg_server.py
py_unidbg_server/commands/__init__.py
py_unidbg_server/commands/edit.py
py_unidbg_server/commands/main.py
py_unidbg_server/commands/start.py
py_unidbg_server/utils/__init__.py
py_unidbg_server/utils/log.py
py_unidbg_server-0.1.0.dist-info/licenses/LICENSE
py_unidbg_server-0.1.0.dist-info/METADATA
py_unidbg_server-0.1.0.dist-info/WHEEL
py_unidbg_server-0.1.0.dist-info/entry_points.txt
py_unidbg_server-0.1.0.dist-info/top_level.txt
py_unidbg_server-0.1.0.dist-info/RECORD
