Metadata-Version: 2.4
Name: py_unidbg_server
Version: 0.1.0
Summary: A JVM microservice based on Python, no need to dive into Java Springboot, infinite scalability
Author: aFunnyStrange
License: BSD-3-Clause
Project-URL: Homepage, https://github.com/aFunnyStrange/py_unidbg_server
Requires-Python: >=3.7
License-File: LICENSE
Requires-Dist: jpype1
Requires-Dist: fastapi
Requires-Dist: gunicorn
Requires-Dist: uvicorn
Dynamic: license-file
